{
  "collected_at": "2026-04-19T10:21:06.869723+00:00",
  "source": "tomtom_traffic_flow",
  "success_count": 8,
  "fail_count": 0,
  "readings": [
    {
      "timestamp": "2026-04-19 10:20:57.814388+00:00",
      "location_name": "sarjapur_road_junction",
      "lat": 12.9165,
      "lon": 77.675,
      "current_speed": 32,
      "free_flow_speed": 36,
      "confidence": 1,
      "congestion_ratio": 1.125
    },
    {
      "timestamp": "2026-04-19 10:20:58.984838+00:00",
      "location_name": "dommasandra_circle",
      "lat": 12.8832,
      "lon": 77.7524,
      "current_speed": 38,
      "free_flow_speed": 38,
      "confidence": 1,
      "congestion_ratio": 1.0
    },
    {
      "timestamp": "2026-04-19 10:21:00.201655+00:00",
      "location_name": "chembenahalli",
      "lat": 12.8793,
      "lon": 77.7616,
      "current_speed": 38,
      "free_flow_speed": 38,
      "confidence": 1,
      "congestion_ratio": 1.0
    },
    {
      "timestamp": "2026-04-19 10:21:01.536774+00:00",
      "location_name": "varthur_gunjur_junction",
      "lat": 12.9265,
      "lon": 77.7377,
      "current_speed": 32,
      "free_flow_speed": 36,
      "confidence": 1,
      "congestion_ratio": 1.125
    },
    {
      "timestamp": "2026-04-19 10:21:02.740761+00:00",
      "location_name": "sarjapur_town_center",
      "lat": 12.86,
      "lon": 77.786,
      "current_speed": 38,
      "free_flow_speed": 38,
      "confidence": 1,
      "congestion_ratio": 1.0
    },
    {
      "timestamp": "2026-04-19 10:21:03.973337+00:00",
      "location_name": "carmelaram_junction",
      "lat": 12.9125,
      "lon": 77.7056,
      "current_speed": 24,
      "free_flow_speed": 26,
      "confidence": 0.953523,
      "congestion_ratio": 1.083
    },
    {
      "timestamp": "2026-04-19 10:21:05.162914+00:00",
      "location_name": "harlur_road_junction",
      "lat": 12.908,
      "lon": 77.676,
      "current_speed": 26,
      "free_flow_speed": 26,
      "confidence": 1,
      "congestion_ratio": 1.0
    },
    {
      "timestamp": "2026-04-19 10:21:06.352923+00:00",
      "location_name": "iblur_wipro_junction",
      "lat": 12.9209,
      "lon": 77.6653,
      "current_speed": 25,
      "free_flow_speed": 25,
      "confidence": 1,
      "congestion_ratio": 1.0
    }
  ]
}